README.md
setup.py
entyty/__init__.py
entyty/__log__.py
entyty/__main__.py
entyty.egg-info/PKG-INFO
entyty.egg-info/SOURCES.txt
entyty.egg-info/dependency_links.txt
entyty.egg-info/requires.txt
entyty.egg-info/top_level.txt
entyty/_entity/__init__.py
entyty/_entity/_base_entity.py
entyty/_entity/_entity.py
entyty/_entity/_grid_entity.py